devjournal/__about__.py
devjournal/__init__.py
devjournal/__main__.py
devjournal/config.py
devjournal/constants.py
devjournal/edit.py
devjournal/entry.py
devjournal/git.py
devjournal/commands/add.py
devjournal/commands/delete.py
devjournal/commands/edit.py
devjournal/commands/find.py
devjournal/commands/log.py
devjournal/commands/setup.py
devjournal/git_scripts/__init__.py
devjournal/git_scripts/add_commit_pull_rebase_push.py
devjournal/git_scripts/pull_rebase.py
devjournal-0.7.dist-info/METADATA
devjournal-0.7.dist-info/WHEEL
devjournal-0.7.dist-info/entry_points.txt
devjournal-0.7.dist-info/licenses/LICENSE.md
devjournal-0.7.dist-info/RECORD
