Metadata-Version: 2.1
Name: devjournal
Version: 0.7
Author-email: Filip Lange <filip.lange@ericsson.com>
License-File: LICENSE.md
Classifier: Development Status :: 4 - Beta
Classifier: Programming Language :: Python
Classifier: Programming Language :: Python :: 3.7
Classifier: Programming Language :: Python :: 3.8
Classifier: Programming Language :: Python :: 3.9
Classifier: Programming Language :: Python :: 3.10
Classifier: Programming Language :: Python :: 3.11
Classifier: Programming Language :: Python :: Implementation :: CPython
Classifier: Programming Language :: Python :: Implementation :: PyPy
Requires-Python: >=3.7
Requires-Dist: gitpython==3.1.29
Requires-Dist: rich==12.6.0
Requires-Dist: tomli==2.0.1
Requires-Dist: typer==0.7.0
